{"stocks":[{"company_name":"Dow Jones Industrial Average","ticker":"DJI2MN","logo_small":null,"logo_large":null,"last":35294.76,"previous":34912.56,"change":382.2,"change_percent":1.09,"change_icon":"http://cdnimgd.screenfeed.com/financial/icons/standard/up.png","time_last":"2021-10-16T18:45:29.0389649Z","day_open":35023.63,"day_high":35315.94,"day_low":35023.63,"volume":3278648},{"company_name":"S&P 500","ticker":"SPX","logo_small":null,"logo_large":null,"last":4471.37,"previous":4438.26,"change":33.11,"change_percent":0.75,"change_icon":"http://cdnimgd.screenfeed.com/financial/icons/standard/up.png","time_last":"2021-10-16T18:45:28.1349184Z","day_open":4447.69,"day_high":4475.82,"day_low":4447.69,"volume":0},{"company_name":"NASDAQ 100","ticker":"NDX","logo_small":null,"logo_large":null,"last":15146.92,"previous":15052.42,"change":94.5,"change_percent":0.63,"change_icon":"http://cdnimgd.screenfeed.com/financial/icons/standard/up.png","time_last":"2021-10-16T18:45:28.1349184Z","day_open":15098.97,"day_high":15150.14,"day_low":15064.59,"volume":0}]}